.gitignore
HISTORY.rst
README.rst
setup.py
django_ipauth.egg-info/PKG-INFO
django_ipauth.egg-info/SOURCES.txt
django_ipauth.egg-info/dependency_links.txt
django_ipauth.egg-info/not-zip-safe
django_ipauth.egg-info/requires.txt
django_ipauth.egg-info/top_level.txt
ipauth/__init__.py
ipauth/admin.py
ipauth/backend.py
ipauth/models.py
ipauth/views.py
ipauth/tests/__init__.py
ipauth/tests/models.py