Metadata-Version: 1.0
Name: django-ipauth
Version: 0.4.1
Summary: IP Authentication for Django
Home-page: http://www.arch.tamu.edu
Author: TAMU COA ITS
Author-email: webadmin@arch.tamu.edu
License: UNKNOWN
Keywords: django auth backend
Platform: UNKNOWN
Classifier: Framework :: Django
Classifier: Development Status :: 3 - Alpha
Classifier: Programming Language :: Python
Classifier: Topic :: Software Development :: Libraries :: Python Modules
